WarzoneStats/Api.py
WarzoneStats/ApiGG.py
WarzoneStats/ParserGG.py
WarzoneStats/__init__.py
WarzoneStats-0.1.2.dist-info/LICENSE
WarzoneStats-0.1.2.dist-info/METADATA
WarzoneStats-0.1.2.dist-info/WHEEL
WarzoneStats-0.1.2.dist-info/top_level.txt
WarzoneStats-0.1.2.dist-info/RECORD
