Metadata-Version: 2.1
Name: WarzoneStats
Version: 0.1.2
Summary: Python wrapper for the COD API (Warzone) as well as wzstats.gg, with some useful functions to process and parse the stat responses.
Home-page: https://github.com/valtov/WarzoneStats
Author: valtov
Author-email: <vladialtv@gmail.com>
Keywords: python,warzone,tracker,tracker.gg,sbmm,kd
Classifier: Development Status :: 2 - Pre-Alpha
Classifier: Intended Audience :: Developers
Classifier: Programming Language :: Python :: 3
Classifier: Operating System :: Unix
Classifier: Operating System :: MacOS :: MacOS X
Classifier: Operating System :: Microsoft :: Windows
License-File: LICENSE
Requires-Dist: requests
